groupme_bot/__init__.py
groupme_bot/application.py
groupme_bot/attachment.py
groupme_bot/bot.py
groupme_bot/callback.py
groupme_bot/groupme.py
groupme_bot/tests/__init__.py
groupme_bot/tests/test_application.py
groupme_bot/tests/test_attachment.py
groupme_bot/tests/test_callback.py
groupme_bot-0.2.13.dist-info/LICENSE
groupme_bot-0.2.13.dist-info/METADATA
groupme_bot-0.2.13.dist-info/WHEEL
groupme_bot-0.2.13.dist-info/RECORD
