Metadata-Version: 2.1
Name: groupme-bot
Version: 0.2.13
Summary: A simple bot builder for GroupMe
Home-page: https://github.com/brandenc40/groupme-bot
License: MIT
Author: Branden Colen
Author-email: brandencolen@gmail.com
Requires-Python: >=3.11,<4.0
Classifier: Development Status :: 4 - Beta
Classifier: Intended Audience :: Developers
Classifier: License :: OSI Approved :: MIT License
Classifier: Programming Language :: Python :: 3
Classifier: Programming Language :: Python :: 3.11
Classifier: Programming Language :: Python :: 3.10
Classifier: Programming Language :: Python :: 3.6
Classifier: Programming Language :: Python :: 3.7
Classifier: Programming Language :: Python :: 3.8
Classifier: Programming Language :: Python :: 3.9
Classifier: Topic :: Software Development :: Libraries :: Python Modules
Requires-Dist: APScheduler (>=3.10.1,<4.0.0)
Requires-Dist: httpx (>=0.24.1,<0.25.0)
Requires-Dist: starlette (>=0.28.0,<0.29.0)
Requires-Dist: uvicorn[standard] (>=0.22.0,<0.23.0)
Project-URL: Repository, https://github.com/brandenc40/groupme-bot
